kubernetes_readonly_mcp/__init__.py
kubernetes_readonly_mcp/server.py
kubernetes_readonly_mcp-0.1.3.dist-info/licenses/LICENSE
kubernetes_readonly_mcp-0.1.3.dist-info/METADATA
kubernetes_readonly_mcp-0.1.3.dist-info/WHEEL
kubernetes_readonly_mcp-0.1.3.dist-info/entry_points.txt
kubernetes_readonly_mcp-0.1.3.dist-info/top_level.txt
kubernetes_readonly_mcp-0.1.3.dist-info/RECORD
