Metadata-Version: 2.4
Name: kubernetes-readonly-mcp
Version: 0.1.3
Summary: A read-only Kubernetes MCP server for safely interacting with Kubernetes clusters
Author-email: Vijay Kodam <16428721+vijaykodam@users.noreply.github.com>
License:                                  Apache License
Project-URL: Homepage, https://github.com/vijaykodam/kubernetes-readonly-mcp
Project-URL: Bug Tracker, https://github.com/vijaykodam/kubernetes-readonly-mcp/issues
Project-URL: Documentation, https://github.com/vijaykodam/kubernetes-readonly-mcp#readme
Classifier: Development Status :: 3 - Alpha
Classifier: Intended Audience :: Developers
Classifier: License :: OSI Approved :: Apache Software License
Classifier: Programming Language :: Python :: 3
Classifier: Programming Language :: Python :: 3.10
Classifier: Programming Language :: Python :: 3.11
Classifier: Topic :: Software Development :: Libraries
Classifier: Topic :: System :: Systems Administration
Requires-Python: >=3.8
License-File: LICENSE
Requires-Dist: fastmcp>=2.0.0
Requires-Dist: kubernetes>=28.1.0
Provides-Extra: dev
Requires-Dist: pytest>=7.0.0; extra == "dev"
Requires-Dist: black>=23.0.0; extra == "dev"
Requires-Dist: isort>=5.12.0; extra == "dev"
Requires-Dist: flake8>=6.0.0; extra == "dev"
Dynamic: license-file
